## Class file structure



## 3、访问标志





## 5、字段表集合

字段表（field_info）用于描述接口或者类中声明的变量。Java语言中的“字段”（Field）包括类级别变量以及实例级别变量，但不包括在方法内部声明的局部变量。

字段可以包括的修饰符：

- 字段的作用域：public、private、protected修饰符
- 是实例变量还是类变量：static修饰符
- 可变性：final修饰符
- 并发可见性：volatile修饰符，是否强制从主内存读写
- 可否被序列化：transient修饰符
- 字段数据类型：基本类型、对象、数组
- 字段名称

> 上述修饰符中，除了字段数据类型和字段名称之外，其他都是布尔类型，使用标志位来表示。

*字段表结构：*

```
field_info {
    u2 access_flags;
    u2 name_index;
    u2 descriptor_index;
    u2 attributes_count;
    attribute_info attributes[attributes_count];
}
```

结构体field_info的项目如下：

- access_flags：字段的修饰符，与类中的项目access_flags类似。

  *可以设置的标志位和含义如下表所示：*

  | flag name       | flag value | 含义                     |
  | --------------- | ---------- | ------------------------ |
  | `ACC_PUBLIC`    | `0x0001`   | 字段是否public           |
  | `ACC_PRIVATE`   | `0x0002`   | 字段是否private          |
  | `ACC_PROTECTED` | `0x0004`   | 字段是否protected        |
  | `ACC_STATIC`    | `0x0008`   | 字段是否static           |
  | `ACC_FINAL`     | `0x0010`   | 字段是否final            |
  | `ACC_VOLATILE`  | `0x0040`   | 字段是否volatile         |
  | `ACC_TRANSIENT` | `0x0080`   | 字段是否transient        |
  | `ACC_SYNTHETIC` | `0x1000`   | 字段是否由编译器自动产生 |
  | `ACC_ENUM`      | `0x4000`   | 字段是否`enum`           |

  Note：上述表格中列出的flag value仅仅是二进制的16进制表示，因此`ACC_PRIVATE`的二进制表示为`00000000 00000010`，`ACC_STATIC`的二进制表示为`00000000 00001000`，如果字段声明为`private static`，则二进制表示为`00000000 00001010`，对应的十六进制为`0x000A`。所以，在解析Class文件的时候可能会发现对应字段的flag value为`0x0009`、`0x000A`等，与上述表格中的flag value没有匹配的情况。以此类推，其他组合也是一样的。

- name_index：对常量池项的引用，代表字段的简单名称。

- descriptor_index：对常量池项的引用，代表字段的描述符。

- attributes_count：字段属性表数量。

- attributes[attributes_count]：



字段表集合中不会列出父类或父接口中继承而来的字段，但有可能出现原本Java代码之中不存在的字段，譬如在内部类中为了保持对外部类的访问性，编译器就会自动添加指向外部类实例的字段。另外，在Java语言中字段是无法重载的，两个字段的数据类型，修饰符不管是否相同，都必须使用不一样的名称，但是对于Class文件格式来讲，只要两个字段的描述符不是完全相同，那字段重名就是合法的。



## 6、方法表集合



方法表结构

```
method_info {
    u2 access_flags;
    u2 name_index;
    u2 descriptor_index;
    u2 attributes_count;
    attribute_info attributes[attributes_count];
}
```
结构体method_info的项目如下：

- access_flags：方法的修饰符，与类中的项目access_flags类似。

  *可以设置的标志位和含义如下表所示：*

- | flag name          | flag value | 含义                           |
  | ------------------ | ---------- | ------------------------------ |
  | `ACC_PUBLIC`       | `0x0001`   | 方法是否为public               |
  | `ACC_PRIVATE`      | `0x0002`   | 方法是否为private              |
  | `ACC_PROTEDTED`    | `0x0004`   | 方法是否为protected            |
  | `ACC_STATIC`       | `0x0008`   | 方法是否为static               |
  | `ACC_FINAL`        | `0x0010`   | 方法是否为final                |
  | `ACC_SYNCHRONIZED` | `0x0020`   | 方法是否为synchronized         |
  | `ACC_BRIDGE`       | `0x0040`   | 方法是否由编译器产生的桥接方法 |
  | `ACC_VARARGS`      | `0x0080`   | 方法是否接受不定参数           |
  | `ACC_NATIVE`       | `0x0100`   | 方法是否为native               |
  | `ACC_ABSTRACT`     | `0x0400`   | 方法是否为abstract             |
  | `ACC_STRICTFP`     | `0x0800`   | 方法是否为strictfp             |
  | `ACC_SYNTHETIC`    | `0x1000`   | 方法是否由编译器自动产生       |

- name_index：对常量池项的引用，代表方法的简单名称。

- descriptor_index：对常量池项的引用，代表方法的描述符。

- attributes_count：方法属性表数量。

- attributes[attributes_count]：





### case analysis

```java
package com.example.jvm.clazz;
public class TestClass {
    private int m;
    public int inc(){
        return m + 1;
    }
}
```





```java
CA FE BA BE 00 00 00 36 00 13 0A 00 04 00 0F 09 
00 03 00 10 07 00 11 07 00 12 01 00 01 6D 01 00 
01 49 01 00 06 3C 69 6E 69 74 3E 01 00 03 28 29 
56 01 00 04 43 6F 64 65 01 00 0F 4C 69 6E 65 4E 
75 6D 62 65 72 54 61 62 6C 65 01 00 03 69 6E 63 
01 00 03 28 29 49 01 00 0A 53 6F 75 72 63 65 46 
69 6C 65 01 00 0E 54 65 73 74 43 6C 61 73 73 2E 
6A 61 76 61 0C 00 07 00 08 0C 00 05 00 06 01 00 
1F 63 6F 6D 2F 65 78 61 6D 70 6C 65 2F 6A 76 6D 
2F 63 6C 61 7A 7A 2F 54 65 73 74 43 6C 61 73 73 
01 00 10 6A 61 76 61 2F 6C 61 6E 67 2F 4F 62 6A 
65 63 74 00 21 00 03 00 04 00 00 00 01 00 02 00 
05 00 06 00 00 00 02 00 01 00 07 00 08 00 01 00 
09 00 00 00 1D 00 01 00 01 00 00 00 05 2A B7 00 
01 B1 00 00 00 01 00 0A 00 00 00 06 00 01 00 00 
00 03 00 01 00 0B 00 0C 00 01 00 09 00 00 00 1F 
00 02 00 01 00 00 00 07 2A B4 00 02 04 60 AC 00 
00 00 01 00 0A 00 00 00 06 00 01 00 00 00 08 00 
01 00 0D 00 00 00 02 00 0E  
```

#### magic

`CA FE BA BE`

#### minor_version

`00 00` 小版本

#### magic_version

`00 36` 大版本

#### constant Pool

由于常量池中常量的数量是固定的，所以在常量池的入口需要放置一项u2可惜的数据，代表常量池容量计数值（constant_pool_count）。与Java中语言习惯不一样的是，这个容量计数是从1而不是从0开始，例如常量池容量为十六进制数0x13，即十进制19，这就代表常量池中有18向常量，索引值范围为1~18。设计者将第0项常量空出来是有特殊考虑的，这样做的目的在于满足后面某些指向常量池的索引值的数据在特定情况下需要表达“不引用任何一个常量池项目”的含义，这种情况就可以把索引值置位0来表示。

注意：Class文件结构只有常量池的容量计数是从1开始，对于其他集合类型，包括接口索引集合、字段表集合、方法表集合等的容量计数都与一般习惯相同，是从0开始的。

首先是常量池第0位

`00`

##### constant_pool_count

十六进制数0x13，即十进制数19，表示当前常量池中有18个常量。

##### constant_pool[constant_pool_count - 1]

1. **The one constant**

   tag值为0x0A，即十进制10，查看**常量池项目类型**表，可知为`CONSTANT_Methodref_info`表，共占用5个字节，如下：

   ```
   CONSTANT_Methodref_info {
       u1 tag;
       u2 class_index;
       u2 name_and_type_index;
   }
   ```

   十六进制数：0A 00 04 00 0F

2. **The twe constant**

   tag值为0x09，即十进制9，查看**常量池项目类型**表，可知为`CONSTANT_Fieldref_info`表，共占用5个字节，如下：

   ```
   CONSTANT_Fieldref_info {
       u1 tag;
       u2 class_index;
       u2 name_and_type_index;
   }
   ```

   十六进制数：09 00 03 00 10

3. **The third constant**

   tag值为0x07，即十进制7，查看**常量池项目类型**表，可知为`CONSTANT_Class_info`表，共占用3个字节，如下：

   ```
   CONSTANT_Class_info {
       u1 tag;
       u2 name_index;
   }
   ```

   十六进制数：07 00 11

4. **The four constant**

   07 00 12

5. **The five constant**

   tag值为0x01，即十进制1，查看**常量池项目类型**表，可知为`CONSTANT_Utf8_info`表，共占用1+2+length个字节，如下：

   ```
   CONSTANT_Utf8_info {
       u1 tag;
       u2 length;
       u1 bytes[length];
   }
   ```

   十六进制数：01 00 01 6D

01 00 01 => 6D => m

6. **The six constant**

   tag值为0x01，

第六个常量

01 00  01 => 49 => I

第七个常量

01 00 06 => 3C 69 6E 69 74 3E => <init>

第八个常量

01 00 03 => 28 29 56 => ()V

第九个常量

01 00 04 => 43 6F 64 65 => Code

第十个常量

01 00 0F => 4C 69 6E 65 4E 75 6D 62 65 72 54 61 62 6C 65 => LineNumberTable

第十一个常量

01 00 03 =>69 6E 63 => inc

第十二个常量

01 00 03 =>28 29 49 => ()I

第十三个常量

01 00 0A=>53 6F 75 72 63 65 46 69 6C 65 => SourceFile

第十四个常量

01 00 0E=>54 65 73 74 43 6C 61 73 73 2E 6A 61 76 61=>TestClass.java

第十五个常量

0x0C = 12,`CONSTANT_NameAndType_info`

```
CONSTANT_NameAndType_info {
    u1 tag;
    u2 name_index;
    u2 descriptor_index;
}
```

0C 00 07 00 08

第十六个常量

0C 00 05 00 06

第十七个常量

01 00 1F=>63 6F 6D 2F 65 78 61 6D 70 6C 65 2F 6A 76 6D 2F 63 6C 61 7A 7A 2F 54 65 73 74 43 6C 61 73 73

=>com/example/jvm/clazz/TestClass

第十八个常量

01 00 10=>6A 61 76 61 2F 6C 61 6E 67 2F 4F 62 6A 65 63 74=>java/lang/Object



#### access_flags

紧接着是访问标志符

0x0021

#### this_class

0x0003

#### super_class

0x0004

#### interfaces_count

0x0000

#### interfaces[interfaces_count]



#### fields

继类索引，父类索引，接口索引之后是字段表集合，字段表集合如下：

```
field_info {
    u2 access_flags;
    u2 name_index;
    u2 descriptor_index;
    u2 attributes_count;
    attribute_info attributes[attributes_count];
}
```

查看class format structure，在字段表集合之前还有两个字节，代表字段表的数量，所以对应的十六进制数如下：

```
00 01 00 02 00 05 00 06 00 00 00
```

字段表数量为十六进制数0x0001，即十进制1，即只有一个字段。

access_flags为十六进制数0x0002，查看field access flags table，可知访问标志位`private`。

name_index为十六进制数0x0005，即十进制5，对应常量表的第五个常量，查看第五个常量，为`CONSTANT_utf8_info`表，对应字段名称`m`。

descriptor_index为十六进制数0x0006，即十进制6，对应常量表第六个常量，查看第六个常量，为`CONSTANT_utf8_info`，对应字段类型`I`，再查看字段描述符标识字段含义，`I`为基本类型`int`。

attributes_count为十六进制数0x0000，即没有当前字段对应的属性表。

所以，可以得出改字段为：

```java
private int m;
```



##### fields_count

##### fields[fields_count]

#### methods

```
method_info {
    u2 access_flags;
    u2 name_index;
    u2 descriptor_index;
    u2 attributes_count;
    attribute_info attributes[attributes_count];
}
```

00 02 => 00 01 00 07 00 08 00 01

首先两个字节表明是方法的数量

方法表数量为十六进制0x0002，即十进制2，代表有两个方法。

第一个方法：

access_flags为十六进制数0x0001，查看method access flags，访问标记为`public`。

name_index为十六进制数0x0007，即十进制7，对应常量表第7个常量，查看第7个常量，为`CONSTANT_utf8
_info`表，对应方法名称`<init>`，即时构造方法。

descriptor_index为十六进制数0x0008，即十进制8，对应常量表第8个常量，查看第8个常量，为`CONSTANT_utf8_info`表，对应的方法返回值 `()V`。

attributes_count为十六进制数0x0001，



<<<<<<< HEAD
00 
09 00 00 00 1D 00 01 00 01 00 00 00 05 2A B7 00 
01 B1 00 00 00 01 00 0A 00 00 00 06 00 01 00 00 
00 03



00 01 00 0B 00 0C 00 01 00 09 00 00 00 1F 
00 02 00 01 00 00 00 07 2A B4 00 02 04 60 AC 00 

# 00 00 01 00 0A 00 00 00 06 00 01 00 00 00 08

```
attribute_info {
    u2 attribute_name_index;
    u4 attribute_length;
    u1 info[attribute_length];
}
```

00 09 00 00 00 1D 00

attribute_name_index为十六进制0x0009，即十进制9，对应常量表第9个常量，查看第9个常量，为`CONSTANT_utf8_info`表，对应属性名Code。

attribute_length为十六进制0x0000001D，即十进制29，即有29个属性，每个属性站一个字节，即29个字节

info：

```java
14 -                00 01 00 01 00 00 00 05 2A B7 00 
15 - 01 B1 00 00 00 01 00 0A 00 00 00 06 00 01 00 00 
16 - 00 03
```



第一个方法Code属性

- attribute_name_index：00 01
- attribute_length： 
- max_stack：00 01 
- max_locals：00 00 00 05 = 2A B7 00 01 B1
  - 2A => aload_0 => 将第一个引用类型本地变量推送至栈顶
  - B7 => invokespecial => 调用超类的构造方法，实例初始化方法，私有方法
  - 01 => nop => 什么都不做 
  - B1 => return => 从当前方法返回void
- code_length：00 00 00 01
- code：
- exception_table_length：
- ：
- ：
- attributes_count：
- attribute_info：

```
Code_attribute {
    u2 attribute_name_index;
    u4 attribute_length;
    u2 max_stack;
    u2 max_locals;
    u4 code_length;
    u1 code[code_length];
    u2 exception_table_length;
    { 	u2 start_pc;
        u2 end_pc;
        u2 handler_pc;
        u2 catch_type;
    } exception_table[exception_table_length];
    u2 attributes_count;
    attribute_info attributes[attributes_count];
}
```



第二个方法：

```java
16 -       00 01 00 0B 00 0C 00 01 00 09 00 00 00 1F 
17 - 00 02 00 01 00 00 00 07 2A B4 00 02 04 60 AC 00 
18 - 00 00 01 00 0A 00 00 00 06 00 01 00 00 00 08
```

- access_flags : 00 01 = 1 = ACC_PUBLIC

- name_index : 00 0B = 11 = inc

- descriptor_index : 00 0C = 12 =  ()I => ()表示无参，l表示返回值int类型

- attributes_count : 00 01 = 1 = 1个属性

- attribute_info ：

  - attribute_name_index：00 09 = 9 = Code

  - attribute_length：00 00 00 1F = 31

  - info：

    ```java
    17 - 00 02 00 01 00 00 00 07 2A B4 00 02 04 60 AC 00 
    18 - 00 00 01 00 0A 00 00 00 06 00 01 00 00 00 08
    ```





第二个方法Code属性

```java
17 - 00 02^00 01^00 00 00 07^2A B4 00 02 04 60 AC^00 
18 - 00 00 01 00 0A 00 00 00 06 00 01 00 00 00 08
```

- attribute_name_index：00 02
- attribute_length：
- max_stack：00 01 
- max_locals：00 00 00 07 = 2A B4 00 02 04 60^AC
  - aload_0 => 将第一个引用类型本地变量推送至栈顶
  - getfield => 获取指定类的实例域，并将其值压入栈顶
  - iconst_m1 => 将int型_上推送至栈顶
  - iconst_1 =>  将int型1推送至栈顶
  - iadd => 将栈顶两int型数值相加并将结果压入栈顶
  - ireturn => 从当前方法返回int
- code_length：00 00 00 01
- code：
- exception_table_length：
- ：
- ：
- attributes_count：
- attribute_info：



```
Code_attribute {
    u2 attribute_name_index;
    u4 attribute_length;
    u2 max_stack;
    u2 max_locals;
    u4 code_length;
    u1 code[code_length];
    u2 exception_table_length;
    { 	u2 start_pc;
        u2 end_pc;
        u2 handler_pc;
        u2 catch_type;
    } exception_table[exception_table_length];
    u2 attributes_count;
    attribute_info attributes[attributes_count];
}
```



> > > > > > > 2a07e6ce0269c13e6a2f420b105ff9e5fddf674b

##### methods_count



##### methods[methods_count]



```
1  - CA FE BA BE 00 00 00 36 00 13 0A 00 04 00 0F 09 
2  - 00 03 00 10 07 00 11 07 00 12 01 00 01 6D 01 00 
3  - 01 49 01 00 06 3C 69 6E 69 74 3E 01 00 03 28 29 
4  - 56 01 00 04 43 6F 64 65 01 00 0F 4C 69 6E 65 4E 
5  - 75 6D 62 65 72 54 61 62 6C 65 01 00 03 69 6E 63 
6  - 01 00 03 28 29 49 01 00 0A 53 6F 75 72 63 65 46 
7  - 69 6C 65 01 00 0E 54 65 73 74 43 6C 61 73 73 2E 
8  - 6A 61 76 61 0C 00 07 00 08 0C 00 05 00 06 01 00 
9  - 1F 63 6F 6D 2F 65 78 61 6D 70 6C 65 2F 6A 76 6D 
10 - 2F 63 6C 61 7A 7A 2F 54 65 73 74 43 6C 61 73 73 
11 - 01 00 10 6A 61 76 61 2F 6C 61 6E 67 2F 4F 62 6A 
12 - 65 63 74 00 21 00 03 00 04 00 00 00 01 00 02 00 
13 - 05 00 06 00 00@00 02 00 01 00 07 00 08 00 01 00 
14 - 09 00 00 00 1D^00 01 00 01 00 00 00 05 2A B7 00 
15 - 01 B1 00 00 00 01 00 0A 00 00 00 06 00 01 00 00 
16 - 00 03@00 01 00 0B 00 0C 00 01 00 09 00 00 00 1F 
17 - 00 02 00 01 00 00 00 07 2A B4 00 02 04 60 AC 00 
18 - 00 00 01 00 0A 00 00 00 06 00 01 00 00 00 08 00 
19 - 01 00 0D 00 00 00 02 00 0E  
```

<<<<<<< HEAD
CA FE BA BE 00 00 00 36 00 13 0A 00 04 00 0F 09 
00 03 00 10 07 00 11 07 00 12 01 00 01 6D 01 00 
01 49 01 00 06 3C 69 6E 69 74 3E 01 00 03 28 29 
56 01 00 04 43 6F 64 65 01 00 0F 4C 69 6E 65 4E 
75 6D 62 65 72 54 61 62 6C 65 01 00 03 69 6E 63 
01 00 03 28 29 49 01 00 0A 53 6F 75 72 63 65 46 
69 6C 65 01 00 0E 54 65 73 74 43 6C 61 73 73 2E 
6A 61 76 61 0C 00 07 00 08 0C 00 05 00 06 01 00 
1F 63 6F 6D 2F 65 78 61 6D 70 6C 65 2F 6A 76 6D 
2F 63 6C 61 7A 7A 2F 54 65 73 74 43 6C 61 73 73 
01 00 10 6A 61 76 61 2F 6C 61 6E 67 2F 4F 62 6A 
65 63 74 00 21 00 03 00 04 00 00 00 01 00 02 00 
05 00 06 00 00@00 02 00 01 00 07 00 08 00 01 00 
09 00 00 00 1D 00 01 00 01 00 00 00 05 2A B7 00 
01 B1 00 00 00 01 00 0A 00 00 00 06 00 01 00 00 
00 03@00 01 00 0B 00 0C 00 01 00 09 00 00 00 1F 
00 02 00 01 00 00 00 07 2A B4 00 02 04 60 AC 00 
00 00 01 00 0A 00 00 00 06 00 01 00 00 00 08 00 

# 01 00 0D 00 00 00 02 00 0E  





```java
C:\Users\dandelion\Desktop>javap -verbose TestClass.class
Classfile /C:/Users/dandelion/Desktop/TestClass.class
  Last modified 2019年3月28日; size 297 bytes
  MD5 checksum 28c5755e84efa06bef94473ec2353bf0
  Compiled from "TestClass.java"
public class com.example.jvm.clazz.TestClass
  minor version: 0
  major version: 55
  flags: (0x0021) ACC_PUBLIC, ACC_SUPER
  this_class: #3                          // com/example/jvm/clazz/TestClass
  super_class: #4                         // java/lang/Object
  interfaces: 0, fields: 1, methods: 2, attributes: 1
Constant pool:
   #1 = Methodref          #4.#15         // java/lang/Object."<init>":()V
   #2 = Fieldref           #3.#16         // com/example/jvm/clazz/TestClass.m:I
   #3 = Class              #17            // com/example/jvm/clazz/TestClass
   #4 = Class              #18            // java/lang/Object
   #5 = Utf8               m
   #6 = Utf8               I
   #7 = Utf8               <init>
   #8 = Utf8               ()V
   #9 = Utf8               Code
  #10 = Utf8               LineNumberTable
  #11 = Utf8               inc
  #12 = Utf8               ()I
  #13 = Utf8               SourceFile
  #14 = Utf8               TestClass.java
  #15 = NameAndType        #7:#8          // "<init>":()V
  #16 = NameAndType        #5:#6          // m:I
  #17 = Utf8               com/example/jvm/clazz/TestClass
  #18 = Utf8               java/lang/Object
{
  public com.example.jvm.clazz.TestClass();
    descriptor: ()V
    flags: (0x0001) ACC_PUBLIC
    Code:
      stack=1, locals=1, args_size=1
         0: aload_0
         1: invokespecial #1                  // Method java/lang/Object."<init>":()V
         4: return
      LineNumberTable:
        line 2: 0

  public int inc();
    descriptor: ()I
    flags: (0x0001) ACC_PUBLIC
    Code:
      stack=2, locals=1, args_size=1
         0: aload_0
         1: getfield      #2                  // Field m:I
         4: iconst_1
         5: iadd
         6: ireturn
      LineNumberTable:
        line 5: 0
}
SourceFile: "TestClass.java"
>>>>>>> 2a07e6ce0269c13e6a2f420b105ff9e5fddf674b
```







### 常量池的项目类型

| type                               | tag  | description              |
| ---------------------------------- | ---- | ------------------------ |
| `CONSTANT_Utf8_info`               | 1    | UTF-8编码的字符串        |
| `CONSTANT_Integer_info`            | 3    | 整型字面量               |
| `CONSTANT_Float_info`              | 4    | 浮点型字面量             |
| `CONSTANT_Long_info`               | 5    | 长整型字面量             |
| `CONSTANT_Double_info`             | 6    | 双精度浮点型字面量       |
| `CONSTANT_Class_info`              | 7    | 类或接口的符号引用       |
| `CONSTANT_String_info`             | 8    | 字符串类型字面量         |
| `CONSTANT_Fieldref_info`           | 9    | 字段的符号引用           |
| `CONSTANT_Methodref_info`          | 10   | 类中方法的符号引用       |
| `CONSTANT_InterfaceMethodref_info` | 11   | 接口中方法的引用符号     |
| `CONSTANT_NameAndType_info`        | 12   | 字段或方法的部分引用符号 |
| `CONSTANT_MethodHandle_info`       | 15   | 表示方法句柄             |
| `CONSTANT_MethodType_info`         | 16   | 标识方法类型             |
| `CONSTANT_InvokeDenamic_info`      | 18   | 表示一个动态方法的调用点 |



#### `CONSTANT_Utf8_info`





```
CONSTANT_Utf8_info {
    u1 tag;
    u2 length;
    u1 bytes[length];
}
```



#### `CONSTANT_NameAndType_info`

```
CONSTANT_NameAndType_info {
    u1 tag;
    u2 name_index;
    u2 descriptor_index;
}
```





#### `CONSTANT_Fieldref_info`

```
CONSTANT_Fieldref_info {
    u1 tag;
    u2 class_index;
    u2 name_and_type_index;
}
```

#### `CONSTANT_Methodref_info`

```
CONSTANT_Methodref_info {
    u1 tag;
    u2 class_index;
    u2 name_and_type_index;
}
```

#### `CONSTANT_InterfaceMethodref_info`

```
CONSTANT_InterfaceMethodref_info {
    u1 tag;
    u2 class_index;
    u2 name_and_type_index;
}
```



### Access flags table

| flag name      | flag value | 含义                                                         |
| -------------- | ---------- | ------------------------------------------------------------ |
| ACC_PUBLIC     | 0x0001     | 是否为public类型                                             |
| ACC_FINAL      | 0x0010     | 是否被什么为final，只有类可设置                              |
| ACC_SUPER      | 0x0020     | 是否允许使用invokespecial字节码指令的新语意，invokespecial指令的语意在JDK 1.0.2发生过改变，为了区别这条指令使用哪种语意，JDK 1.0.2之后编译出来的类的这个标志都必须为真。 |
| ACC_INTERFACE  | 0x0200     | 标识这是一个接口                                             |
| ACC_ABSTRAT    | 0x0400     | 是否为abstract类型，对于接口或者抽象类来说，此标志值为真，其他类值为假 |
| ACC_SYNTHETIC  | 0x1000     | 标识这个类并非由用户代码产生的                               |
| ACC_ANNOTATION | 0x2000     | 标识这时一个注解                                             |
| ACC_ENUM       | 0x4000     | 标识这是一个枚举                                             |

### Field access flags table

| flag name     | flag value | 含义                     |
| ------------- | ---------- | ------------------------ |
| ACC_PUBLIC    | 0x0001     | 字段是否public           |
| ACC_PRIVATE   | 0x0002     | 字段是否private          |
| ACC_PROTECTED | 0x0004     | 字段是否protected        |
| ACC_STATIC    | 0x0008     | 字段是否static           |
| ACC_FINAL     | 0x0010     | 字段是否final            |
| ACC_VOLATILE  | 0x0040     | 字段是否volatile         |
| ACC_TRANSIENT | 0x0080     | 字段是否transient        |
| ACC_SYNTHETIC | 0x1000     | 字段是否由编译器自动产生 |
| ACC_ENUM      | 0x4000     | 字段是否enum             |



### 描述符标识字段含义

| 标识字段 | 含义           | 标识字段 | 含义                          |
| -------- | -------------- | -------- | ----------------------------- |
| B        | 基本类型byte   | J        | 基本类型long                  |
| C        | 基本类型char   | S        | 基本类型short                 |
| D        | 基本类型double | Z        | 基本类型boolean               |
| F        | 基本类型float  | V        | 特殊类型void                  |
| I        | 基本类型int    | L        | 对象类型，如Ljava/lang/Object |

### Method access flags

| flag name        | flag value | 含义                           |
| ---------------- | ---------- | ------------------------------ |
| ACC_PUBLIC       | 0x0001     | 方法是否为public               |
| ACC_PRIVATE      | 0x0002     | 方法是否为private              |
| ACC_PROTEDTED    | 0x0004     | 方法是否为protected            |
| ACC_STATIC       | 0x0008     | 方法是否为static               |
| ACC_FINAL        | 0x0010     | 方法是否为final                |
| ACC_SYNCHRONIZED | 0x0020     | 方法是否为synchronized         |
| ACC_BRIDGE       | 0x0040     | 方法是否由编译器产生的桥接方法 |
| ACC_VARARGS      | 0x0080     | 方法是否接受不定参数           |
| ACC_NATIVE       | 0x0100     | 方法是否为native               |
| ACC_ABSTRACT     | 0x0400     | 方法是否为abstract             |
| ACC_STRICTFP     | 0x0800     | 方法是否为strictfp             |
| ACC_SYNTHETIC    | 0x1000     | 方法是否由编译器自动产生       |

